tree_sitter_nix/__init__.py
tree_sitter_nix/__init__.pyi
tree_sitter_nix/_binding.pyd
tree_sitter_nix/binding.c
tree_sitter_nix/py.typed
tree_sitter_nix/queries/highlights.scm
tree_sitter_nix/queries/injections.scm
tree_sitter_nix/queries/locals.scm
tree_sitter_nix-0.1.0.dist-info/LICENSE
tree_sitter_nix-0.1.0.dist-info/METADATA
tree_sitter_nix-0.1.0.dist-info/WHEEL
tree_sitter_nix-0.1.0.dist-info/top_level.txt
tree_sitter_nix-0.1.0.dist-info/RECORD
