Metadata-Version: 2.2
Name: tree-sitter-nix
Version: 0.1.0
Summary: Nix grammar for tree-sitter
License: MIT
Project-URL: Homepage, https://github.com/tree-sitter/tree-sitter-nix
Keywords: incremental,parsing,tree-sitter,nix
Classifier: Intended Audience :: Developers
Classifier: Topic :: Software Development :: Compilers
Classifier: Topic :: Text Processing :: Linguistic
Classifier: Typing :: Typed
Requires-Python: >=3.10
License-File: LICENSE
Provides-Extra: core
Requires-Dist: tree-sitter~=0.24; extra == "core"
